setup.py
phoenix_ml/NN.py
phoenix_ml/__init__.py
phoenix_ml/back_prop.py
phoenix_ml/cnn.py
phoenix_ml/data_loader.py
phoenix_ml/data_preprocessing.py
phoenix_ml/evaluation.py
phoenix_ml/forward_prop.py
phoenix_ml/optimization.py
phoenix_ml/runner.py
phoenix_ml/utils_module.py
phoenix_ml/visualization.py
phoenix_ml.egg-info/PKG-INFO
phoenix_ml.egg-info/SOURCES.txt
phoenix_ml.egg-info/dependency_links.txt
phoenix_ml.egg-info/not-zip-safe
phoenix_ml.egg-info/top_level.txt